odoo/addons/base_edi/README.rst
odoo/addons/base_edi/__init__.py
odoo/addons/base_edi/__manifest__.py
odoo/addons/base_edi/data/module_category.xml
odoo/addons/base_edi/i18n/base_edi.pot
odoo/addons/base_edi/i18n/es.po
odoo/addons/base_edi/i18n/fr.po
odoo/addons/base_edi/i18n/hr.po
odoo/addons/base_edi/i18n/it.po
odoo/addons/base_edi/i18n/nl.po
odoo/addons/base_edi/readme/CONTRIBUTORS.md
odoo/addons/base_edi/readme/DESCRIPTION.md
odoo/addons/base_edi/readme/ROADMAP.md
odoo/addons/base_edi/security/edi_groups.xml
odoo/addons/base_edi/static/description/icon.png
odoo/addons/base_edi/static/description/icon.svg
odoo/addons/base_edi/static/description/index.html
odoo/addons/base_edi/tests/__init__.py
odoo/addons/base_edi/tests/test_base_edi.py
odoo/addons/base_edi/views/edi_menu.xml
odoo_addon_base_edi-19.0.1.0.0.3.dist-info/METADATA
odoo_addon_base_edi-19.0.1.0.0.3.dist-info/WHEEL
odoo_addon_base_edi-19.0.1.0.0.3.dist-info/top_level.txt
odoo_addon_base_edi-19.0.1.0.0.3.dist-info/RECORD
