Metadata-Version: 2.1
Name: odoo-addon-base_edi
Version: 19.0.1.0.0.3
Requires-Dist: odoo==19.0.*
Summary: Base module to aggregate EDI features.
Home-page: https://github.com/OCA/edi
License: LGPL-3
Author: ACSONE,Odoo Community Association (OCA)
Author-email: support@odoo-community.org
Classifier: Programming Language :: Python
Classifier: Framework :: Odoo
Classifier: Framework :: Odoo :: 19.0
Classifier: License :: OSI Approved :: GNU Lesser General Public License v3 (LGPLv3)
Classifier: Development Status :: 6 - Mature
